flagcapt/__init__.py
flagcapt/__main__.py
flagcapt-0.3.dist-info/LICENSE
flagcapt-0.3.dist-info/METADATA
flagcapt-0.3.dist-info/WHEEL
flagcapt-0.3.dist-info/entry_points.txt
flagcapt-0.3.dist-info/top_level.txt
flagcapt-0.3.dist-info/RECORD
