Metadata-Version: 2.2
Name: flagcapt
Version: 0.3
Summary: A tool for solving cryptographic challenges in CTFs
Author: 1DH4M
License: MIT
Classifier: Programming Language :: Python :: 3
Classifier: License :: OSI Approved :: MIT License
Classifier: Operating System :: OS Independent
Requires-Python: >=3.6
License-File: LICENSE
Requires-Dist: requests
Requires-Dist: tqdm
Requires-Dist: pycryptodome
Requires-Dist: gmpy2
Requires-Dist: libnum
Requires-Dist: owiener
Requires-Dist: beautifulsoup4
Requires-Dist: lxml
Requires-Dist: urllib3
Dynamic: author
Dynamic: classifier
Dynamic: description
Dynamic: description-content-type
Dynamic: license
Dynamic: requires-dist
Dynamic: requires-python
Dynamic: summary
